agentcraftdb_client/__init__.py
agentcraftdb_client/client.py
agentcraft_db_client-0.1.0.dist-info/METADATA
agentcraft_db_client-0.1.0.dist-info/WHEEL
agentcraft_db_client-0.1.0.dist-info/top_level.txt
agentcraft_db_client-0.1.0.dist-info/RECORD
