Metadata-Version: 2.4
Name: agentcraft-db-client
Version: 0.1.0
Summary: Python SDK for a AgentCraft (Crafted) Vector DB
Author-email: Seyhun Akyurek <info@we-crafted.com>
Requires-Dist: requests
